modbus_mcp/__init__.py
modbus_mcp/cli.py
modbus_mcp/server.py
modbus_mcp/settings.py
modbus_mcp/utils.py
modbus_mcp-0.2.11.dist-info/METADATA
modbus_mcp-0.2.11.dist-info/WHEEL
modbus_mcp-0.2.11.dist-info/entry_points.txt
modbus_mcp-0.2.11.dist-info/licenses/LICENSE
modbus_mcp-0.2.11.dist-info/RECORD
