Metadata-Version: 2.4
Name: modbus-mcp
Version: 0.2.11
Summary: A Model Context Protocol (MCP) server for Modbus
License-File: LICENSE
Requires-Python: >=3.13
Requires-Dist: fastmcp>=2.13.0
Requires-Dist: pydantic-settings>=2.10.0
Requires-Dist: pymodbus>=3.10.0
Requires-Dist: typer>=0.16.0
